serbiacard/CelikApi.dll
serbiacard/__init__.py
serbiacard/card.py
serbiacard/card_additional.py
serbiacard/eVehicleRegistrationAPI.dll
serbiacard/eVehicleRegistrationCOM.dll
serbiacard/try.py
serbiacard-5.0.0.dist-info/METADATA
serbiacard-5.0.0.dist-info/WHEEL
serbiacard-5.0.0.dist-info/RECORD
